{"p01rm": {"default": 1.824, "type": "float"}, "p01ep": {"default": 0.17, "type": "float"}, "p02rm": {"default": 0.6, "type": "float"}, "p02ep": {"default": 0.0157, "type": "float"}, "p03rm": {"default": 1.908, "type": "float"}, "p03ep": {"default": 0.1094, "type": "float"}, "p04rm": {"default": 1.1, "type": "float"}, "p04ep": {"default": 0.0157, "type": "float"}, "p05rm": {"default": 1.387, "type": "float"}, "p05ep": {"default": 0.0157, "type": "float"}, "p06rm": {"default": 1.721, "type": "float"}, "p06ep": {"default": 0.2104, "type": "float"}, "p07rm": {"default": 0.0, "type": "float"}, "p07ep": {"default": 0.0, "type": "float"}, "p08rm": {"default": 1.908, "type": "float"}, "p08ep": {"default": 0.086, "type": "float"}, "p09rm": {"default": 1.6612, "type": "float"}, "p09ep": {"default": 0.21, "type": "float"}, "p10rm": {"default": 1.487, "type": "float"}, "p10ep": {"default": 0.0157, "type": "float"}, "p11rm": {"default": 2.0, "type": "float"}, "p11ep": {"default": 0.25, "type": "float"}, "p12rm": {"default": 1.459, "type": "float"}, "p12ep": {"default": 0.015, "type": "float"}, "p13rm": {"default": 1.409, "type": "float"}, "p13ep": {"default": 0.015, "type": "float"}, "p14rm": {"default": 1.359, "type": "float"}, "p14ep": {"default": 0.015, "type": "float"}, "p15rm": {"default": 1.9480000000000002, "type": "float"}, "p15ep": {"default": 0.265, "type": "float"}, "p16rm": {"default": 1.7683, "type": "float"}, "p16ep": {"default": 0.152, "type": "float"}, "p17rm": {"default": 0.0, "type": "float"}, "p17ep": {"default": 0.0, "type": "float"}}